csvmedkit/__about__.py
csvmedkit/__init__.py
csvmedkit/exceptions.py
csvmedkit-0.0.9.13.dist-info/AUTHORS.rst
csvmedkit-0.0.9.13.dist-info/LICENSE
csvmedkit-0.0.9.13.dist-info/METADATA
csvmedkit-0.0.9.13.dist-info/WHEEL
csvmedkit-0.0.9.13.dist-info/entry_points.txt
csvmedkit-0.0.9.13.dist-info/top_level.txt
csvmedkit-0.0.9.13.dist-info/RECORD
